{"i":"root","n":"TinyBase","u":"/","p":1,"o":1,"_":[{"i":"G","n":"Guides","u":"/guides/","p":1},{"i":"D2","n":"Demos","u":"/demos/","p":1},{"i":"api","n":"API","u":"/api/","p":1,"o":1,"_":[{"i":"e","n":"The Essentials","u":"/api/the-essentials/","p":1},{"i":"s","n":"store","u":"/api/store/","r":1,"p":1},{"i":"m","n":"mergeable-store","u":"/api/mergeable-store/","r":1,"p":1},{"i":"m3","n":"metrics","u":"/api/metrics/","r":1,"p":1},{"i":"i","n":"indexes","u":"/api/indexes/","r":1,"p":1},{"i":"r","n":"relationships","u":"/api/relationships/","r":1,"p":1},{"i":"q","n":"queries","u":"/api/queries/","r":1,"p":1},{"i":"c","n":"checkpoints","u":"/api/checkpoints/","r":1,"p":1},{"i":"c3","n":"common","u":"/api/common/","r":1,"p":1},{"i":"p","n":"persisters","u":"/api/persisters/","r":1,"p":1},{"i":"p2","n":"persister-automerge","u":"/api/persister-automerge/","r":1,"p":1},{"i":"p3","n":"persister-browser","u":"/api/persister-browser/","r":1,"p":1},{"i":"p4","n":"persister-cr-sqlite-wasm","u":"/api/persister-cr-sqlite-wasm/","r":1,"p":1},{"i":"p5","n":"persister-durable-object-sql-storage","u":"/api/persister-durable-object-sql-storage/","r":1,"p":1},{"i":"p6","n":"persister-durable-object-storage","u":"/api/persister-durable-object-storage/","r":1,"p":1},{"i":"p7","n":"persister-electric-sql","u":"/api/persister-electric-sql/","r":1,"p":1},{"i":"p8","n":"persister-expo-sqlite","u":"/api/persister-expo-sqlite/","r":1,"p":1},{"i":"p9","n":"persister-file","u":"/api/persister-file/","r":1,"p":1},{"i":"p10","n":"persister-indexed-db","u":"/api/persister-indexed-db/","r":1,"p":1},{"i":"p11","n":"persister-libsql","u":"/api/persister-libsql/","r":1,"p":1},{"i":"p12","n":"persister-partykit-client","u":"/api/persister-partykit-client/","r":1,"p":1},{"i":"p13","n":"persister-partykit-server","u":"/api/persister-partykit-server/","r":1,"p":1},{"i":"p14","n":"persister-pglite","u":"/api/persister-pglite/","r":1,"p":1},{"i":"p15","n":"persister-postgres","u":"/api/persister-postgres/","r":1,"p":1},{"i":"p16","n":"persister-powersync","u":"/api/persister-powersync/","r":1,"p":1},{"i":"p17","n":"persister-react-native-mmkv","u":"/api/persister-react-native-mmkv/","r":1,"p":1},{"i":"p18","n":"persister-react-native-sqlite","u":"/api/persister-react-native-sqlite/","r":1,"p":1},{"i":"p19","n":"persister-remote","u":"/api/persister-remote/","r":1,"p":1},{"i":"p20","n":"persister-sqlite-bun","u":"/api/persister-sqlite-bun/","r":1,"p":1},{"i":"p21","n":"persister-sqlite-wasm","u":"/api/persister-sqlite-wasm/","r":1,"p":1},{"i":"p22","n":"persister-sqlite3","u":"/api/persister-sqlite3/","r":1,"p":1},{"i":"p23","n":"persister-yjs","u":"/api/persister-yjs/","r":1,"p":1},{"i":"s50","n":"synchronizers","u":"/api/synchronizers/","r":1,"p":1},{"i":"s53","n":"synchronizer-broadcast-channel","u":"/api/synchronizer-broadcast-channel/","r":1,"p":1},{"i":"s56","n":"synchronizer-local","u":"/api/synchronizer-local/","r":1,"p":1},{"i":"s59","n":"synchronizer-ws-client","u":"/api/synchronizer-ws-client/","r":1,"p":1},{"i":"s62","n":"synchronizer-ws-server","u":"/api/synchronizer-ws-server/","r":1,"p":1},{"i":"s63","n":"synchronizer-ws-server-durable-object","u":"/api/synchronizer-ws-server-durable-object/","r":1,"p":1},{"i":"s64","n":"synchronizer-ws-server-simple","u":"/api/synchronizer-ws-server-simple/","r":1,"p":1},{"i":"m4","n":"middleware","u":"/api/middleware/","r":1,"p":1},{"i":"s65","n":"schematizer-arktype","u":"/api/schematizer-arktype/","r":1,"p":1},{"i":"s66","n":"schematizer-effect","u":"/api/schematizer-effect/","r":1,"p":1},{"i":"s67","n":"schematizer-typebox","u":"/api/schematizer-typebox/","r":1,"p":1},{"i":"s68","n":"schematizer-valibot","u":"/api/schematizer-valibot/","r":1,"p":1},{"i":"s69","n":"schematizer-yup","u":"/api/schematizer-yup/","r":1,"p":1},{"i":"s70","n":"schematizer-zod","u":"/api/schematizer-zod/","r":1,"p":1},{"i":"s71","n":"schematizers","u":"/api/schematizers/","r":1,"p":1},{"i":"u","n":"ui-react","u":"/api/ui-react/","r":1,"p":1},{"i":"u2","n":"ui-react-dom","u":"/api/ui-react-dom/","r":1,"p":1},{"i":"u3","n":"ui-react-inspector","u":"/api/ui-react-inspector/","r":1,"p":1},{"i":"u4","n":"ui-svelte","u":"/api/ui-svelte/","r":1,"p":1,"o":1,"_":[{"i":"u4/F50","n":"Functions","u":"/api/ui-svelte/functions/","p":1,"o":1,"_":[{"i":"u4/F50/G44","n":"Getter functions","u":"/api/ui-svelte/functions/getter/","p":1,"o":1,"_":[{"i":"cSI","n":"createStoreIds","u":"/api/ui-svelte/functions/getter/createstoreids/","r":1},{"i":"gISTI","n":"getIndexStoreTableId","u":"/api/ui-svelte/functions/getter/getindexstoretableid/","r":1},{"i":"gRSTI","n":"getRelationshipsStoreTableIds","u":"/api/ui-svelte/functions/getter/getrelationshipsstoretableids/","r":1},{"i":"gS94","n":"getStore","u":"/api/ui-svelte/functions/getter/getstore/","r":1},{"i":"rS","n":"resolveStore","u":"/api/ui-svelte/functions/getter/resolvestore/","r":1},{"i":"cHT","n":"createHasTables","u":"/api/ui-svelte/functions/getter/createhastables/","r":1},{"i":"cT","n":"createTables","u":"/api/ui-svelte/functions/getter/createtables/","r":1},{"i":"cTI","n":"createTableIds","u":"/api/ui-svelte/functions/getter/createtableids/","r":1},{"i":"cHT2","n":"createHasTable","u":"/api/ui-svelte/functions/getter/createhastable/","r":1},{"i":"cHTC","n":"createHasTableCell","u":"/api/ui-svelte/functions/getter/createhastablecell/","r":1},{"i":"cRT","n":"createResultTable","u":"/api/ui-svelte/functions/getter/createresulttable/","r":1,"c":1},{"i":"cRTCI","n":"createResultTableCellIds","u":"/api/ui-svelte/functions/getter/createresulttablecellids/","r":1},{"i":"cT2","n":"createTable","u":"/api/ui-svelte/functions/getter/createtable/","r":1},{"i":"cTCI","n":"createTableCellIds","u":"/api/ui-svelte/functions/getter/createtablecellids/","r":1},{"i":"cLRI","n":"createLinkedRowIds","u":"/api/ui-svelte/functions/getter/createlinkedrowids/","r":1},{"i":"cLRI2","n":"createLocalRowIds","u":"/api/ui-svelte/functions/getter/createlocalrowids/","r":1},{"i":"cRRI","n":"createResultRowIds","u":"/api/ui-svelte/functions/getter/createresultrowids/","r":1},{"i":"cRSRI","n":"createResultSortedRowIds","u":"/api/ui-svelte/functions/getter/createresultsortedrowids/","r":1},{"i":"cRI","n":"createRowIds","u":"/api/ui-svelte/functions/getter/createrowids/","r":1},{"i":"cSRI","n":"createSliceRowIds","u":"/api/ui-svelte/functions/getter/createslicerowids/","r":1},{"i":"cSRI2","n":"createSortedRowIds","u":"/api/ui-svelte/functions/getter/createsortedrowids/","r":1},{"i":"cHR","n":"createHasRow","u":"/api/ui-svelte/functions/getter/createhasrow/","r":1},{"i":"cRRI2","n":"createRemoteRowId","u":"/api/ui-svelte/functions/getter/createremoterowid/","r":1},{"i":"cRR","n":"createResultRow","u":"/api/ui-svelte/functions/getter/createresultrow/","r":1},{"i":"cRRC","n":"createResultRowCount","u":"/api/ui-svelte/functions/getter/createresultrowcount/","r":1},{"i":"cR2","n":"createRow","u":"/api/ui-svelte/functions/getter/createrow/","r":1},{"i":"cRC","n":"createRowCount","u":"/api/ui-svelte/functions/getter/createrowcount/","r":1},{"i":"cCI","n":"createCellIds","u":"/api/ui-svelte/functions/getter/createcellids/","r":1},{"i":"cRCI","n":"createResultCellIds","u":"/api/ui-svelte/functions/getter/createresultcellids/","r":1},{"i":"cC2","n":"createCell","u":"/api/ui-svelte/functions/getter/createcell/","r":1},{"i":"cHC","n":"createHasCell","u":"/api/ui-svelte/functions/getter/createhascell/","r":1},{"i":"cRC2","n":"createResultCell","u":"/api/ui-svelte/functions/getter/createresultcell/","r":1},{"i":"cHV","n":"createHasValues","u":"/api/ui-svelte/functions/getter/createhasvalues/","r":1},{"i":"cV","n":"createValues","u":"/api/ui-svelte/functions/getter/createvalues/","r":1},{"i":"cHV2","n":"createHasValue","u":"/api/ui-svelte/functions/getter/createhasvalue/","r":1},{"i":"cV2","n":"createValue","u":"/api/ui-svelte/functions/getter/createvalue/","r":1},{"i":"cVI","n":"createValueIds","u":"/api/ui-svelte/functions/getter/createvalueids/","r":1},{"i":"cC3","n":"createCheckpoint","u":"/api/ui-svelte/functions/getter/createcheckpoint/","r":1},{"i":"cCI2","n":"createCheckpointIds","u":"/api/ui-svelte/functions/getter/createcheckpointids/","r":1},{"i":"cCI3","n":"createCheckpointsIds","u":"/api/ui-svelte/functions/getter/createcheckpointsids/","r":1},{"i":"cII","n":"createIndexIds","u":"/api/ui-svelte/functions/getter/createindexids/","r":1},{"i":"cII2","n":"createIndexesIds","u":"/api/ui-svelte/functions/getter/createindexesids/","r":1},{"i":"cM3","n":"createMetric","u":"/api/ui-svelte/functions/getter/createmetric/","r":1},{"i":"cMI","n":"createMetricIds","u":"/api/ui-svelte/functions/getter/createmetricids/","r":1},{"i":"cMI2","n":"createMetricsIds","u":"/api/ui-svelte/functions/getter/createmetricsids/","r":1},{"i":"cPI","n":"createPersisterIds","u":"/api/ui-svelte/functions/getter/createpersisterids/","r":1},{"i":"cPS","n":"createPersisterStatus","u":"/api/ui-svelte/functions/getter/createpersisterstatus/","r":1},{"i":"cQI","n":"createQueriesIds","u":"/api/ui-svelte/functions/getter/createqueriesids/","r":1},{"i":"cQI2","n":"createQueryIds","u":"/api/ui-svelte/functions/getter/createqueryids/","r":1},{"i":"cRI2","n":"createRelationshipIds","u":"/api/ui-svelte/functions/getter/createrelationshipids/","r":1},{"i":"cRI3","n":"createRelationshipsIds","u":"/api/ui-svelte/functions/getter/createrelationshipsids/","r":1},{"i":"cSI2","n":"createSliceIds","u":"/api/ui-svelte/functions/getter/createsliceids/","r":1},{"i":"cSI3","n":"createSynchronizerIds","u":"/api/ui-svelte/functions/getter/createsynchronizerids/","r":1},{"i":"cSS","n":"createSynchronizerStatus","u":"/api/ui-svelte/functions/getter/createsynchronizerstatus/","r":1},{"i":"gC9","n":"getCheckpoints","u":"/api/ui-svelte/functions/getter/getcheckpoints/","r":1},{"i":"gI","n":"getIndexes","u":"/api/ui-svelte/functions/getter/getindexes/","r":1},{"i":"gM2","n":"getMetrics","u":"/api/ui-svelte/functions/getter/getmetrics/","r":1},{"i":"gP2","n":"getPersister","u":"/api/ui-svelte/functions/getter/getpersister/","r":1},{"i":"gQ","n":"getQueries","u":"/api/ui-svelte/functions/getter/getqueries/","r":1},{"i":"gR4","n":"getRelationships","u":"/api/ui-svelte/functions/getter/getrelationships/","r":1},{"i":"gS95","n":"getSynchronizer","u":"/api/ui-svelte/functions/getter/getsynchronizer/","r":1},{"i":"rC","n":"resolveCheckpoints","u":"/api/ui-svelte/functions/getter/resolvecheckpoints/","r":1},{"i":"rI","n":"resolveIndexes","u":"/api/ui-svelte/functions/getter/resolveindexes/","r":1},{"i":"rM","n":"resolveMetrics","u":"/api/ui-svelte/functions/getter/resolvemetrics/","r":1},{"i":"rP","n":"resolvePersister","u":"/api/ui-svelte/functions/getter/resolvepersister/","r":1},{"i":"rQ","n":"resolveQueries","u":"/api/ui-svelte/functions/getter/resolvequeries/","r":1},{"i":"rR","n":"resolveRelationships","u":"/api/ui-svelte/functions/getter/resolverelationships/","r":1},{"i":"rS2","n":"resolveSynchronizer","u":"/api/ui-svelte/functions/getter/resolvesynchronizer/","r":1}]},{"i":"u4/F50/L109","n":"Listener functions","u":"/api/ui-svelte/functions/listener/","p":1},{"i":"u4/F50/C101","n":"Callback functions","u":"/api/ui-svelte/functions/callback/","p":1},{"i":"u4/F50/C102","n":"Component functions","u":"/api/ui-svelte/functions/component/","p":1},{"i":"u4/F50/P61","n":"Provider functions","u":"/api/ui-svelte/functions/provider/","p":1}]},{"i":"u4/TA27","n":"Type Aliases","u":"/api/ui-svelte/type-aliases/","p":1}]}]}]}